LICENSE.txt
README.md
setup.cfg
setup.py
django_rtk_upfront/__init__.py
django_rtk_upfront/admin.py
django_rtk_upfront/apps.py
django_rtk_upfront/backends.py
django_rtk_upfront/models.py
django_rtk_upfront/validators.py
django_rtk_upfront.egg-info/PKG-INFO
django_rtk_upfront.egg-info/SOURCES.txt
django_rtk_upfront.egg-info/dependency_links.txt
django_rtk_upfront.egg-info/not-zip-safe
django_rtk_upfront.egg-info/requires.txt
django_rtk_upfront.egg-info/top_level.txt
django_rtk_upfront/migrations/0001_initial.py
django_rtk_upfront/migrations/__init__.py
django_rtk_upfront/mutations/__init__.py
django_rtk_upfront/mutations/activateaccount.py
django_rtk_upfront/mutations/registeraccount.py
django_rtk_upfront/queries/__init__.py