Metadata-Version: 2.1
Name: django-rtk-upfront
Version: 0.6.0
Summary: Extension of django-rtk that requires a password in the registration step
Home-page: https://github.com/mnieber/django-rtk-home/blob/main/django-rtk-upfront/README.md
Author: Maarten Nieber
Author-email: hallomaarten@yahoo.com
License: MIT
Platform: UNKNOWN
Requires-Python: >=3.6
License-File: LICENSE.txt
